jupyterlab_whitepaper/__init__.py
jupyterlab_whitepaper/_version.py
jupyterlab_whitepaper-1.0.1.data/data/share/jupyter/labextensions/jupyterlab_whitepaper/install.json
jupyterlab_whitepaper-1.0.1.data/data/share/jupyter/labextensions/jupyterlab_whitepaper/package.json
jupyterlab_whitepaper-1.0.1.data/data/share/jupyter/labextensions/jupyterlab_whitepaper/static/509.26db51b9f0c873587fee.js
jupyterlab_whitepaper-1.0.1.data/data/share/jupyter/labextensions/jupyterlab_whitepaper/static/remoteEntry.8d6bbe322d0ae0ca40f3.js
jupyterlab_whitepaper-1.0.1.data/data/share/jupyter/labextensions/jupyterlab_whitepaper/static/style.js
jupyterlab_whitepaper-1.0.1.data/data/share/jupyter/labextensions/jupyterlab_whitepaper/static/third-party-licenses.json
jupyterlab_whitepaper-1.0.1.data/data/share/jupyter/labextensions/jupyterlab_whitepaper/themes/jupyterlab_whitepaper/06c12e2e30aa664ab014.ttf
jupyterlab_whitepaper-1.0.1.data/data/share/jupyter/labextensions/jupyterlab_whitepaper/themes/jupyterlab_whitepaper/30844063c7df17f9af4a.ttf
jupyterlab_whitepaper-1.0.1.data/data/share/jupyter/labextensions/jupyterlab_whitepaper/themes/jupyterlab_whitepaper/6ca08612c61cdfa09a4d.ttf
jupyterlab_whitepaper-1.0.1.data/data/share/jupyter/labextensions/jupyterlab_whitepaper/themes/jupyterlab_whitepaper/6edc39c3df4fd1d4502a.ttf
jupyterlab_whitepaper-1.0.1.data/data/share/jupyter/labextensions/jupyterlab_whitepaper/themes/jupyterlab_whitepaper/98b1486810c2eccfaa17.ttf
jupyterlab_whitepaper-1.0.1.data/data/share/jupyter/labextensions/jupyterlab_whitepaper/themes/jupyterlab_whitepaper/c3fb0280e4339f6c70ce.ttf
jupyterlab_whitepaper-1.0.1.data/data/share/jupyter/labextensions/jupyterlab_whitepaper/themes/jupyterlab_whitepaper/d113c1ba9654b765d3ad.ttf
jupyterlab_whitepaper-1.0.1.data/data/share/jupyter/labextensions/jupyterlab_whitepaper/themes/jupyterlab_whitepaper/index.css
jupyterlab_whitepaper-1.0.1.data/data/share/jupyter/labextensions/jupyterlab_whitepaper/themes/jupyterlab_whitepaper/index.js
jupyterlab_whitepaper-1.0.1.dist-info/METADATA
jupyterlab_whitepaper-1.0.1.dist-info/WHEEL
jupyterlab_whitepaper-1.0.1.dist-info/licenses/LICENSE
jupyterlab_whitepaper-1.0.1.dist-info/RECORD
