Metadata-Version: 2.3
Name: jupyterlab_whitepaper
Version: 1.0.1
Summary: A simple and minimalistic JupyterLab 4 theme for prototyping ideas, research, and data science.
Project-URL: Homepage, https://github.com/adamvvu/jupyterlab_whitepaper
Project-URL: Bug Tracker, https://github.com/adamvvu/jupyterlab_whitepaper/issues
Project-URL: Repository, https://github.com/adamvvu/jupyterlab_whitepaper
Author-email: Adam Wu <adamwu1@outlook.com>
License: MIT License
License-File: LICENSE
Keywords: jupyter,jupyterlab,jupyterlab-extension,jupyterlab-theme
Classifier: Framework :: Jupyter
Classifier: Framework :: Jupyter :: JupyterLab
Classifier: Framework :: Jupyter :: JupyterLab :: 4
Classifier: Framework :: Jupyter :: JupyterLab :: Extensions
Classifier: Framework :: Jupyter :: JupyterLab :: Extensions :: Prebuilt
Classifier: License :: OSI Approved :: BSD License
Classifier: Programming Language :: Python
Classifier: Programming Language :: Python :: 3
Classifier: Programming Language :: Python :: 3.8
Classifier: Programming Language :: Python :: 3.9
Classifier: Programming Language :: Python :: 3.10
Classifier: Programming Language :: Python :: 3.11
Classifier: Programming Language :: Python :: 3.12
Requires-Python: >=3.8
